mydomuk/__init__.py
mydomuk/sysmon/__init__.py
mydomuk/sysmon/__main__.py
mydomuk/sysmon/includes/__init__.py
mydomuk/sysmon/includes/config.py
mydomuk/sysmon/includes/constants.py
mydomuk/sysmon/includes/ha_device.py
mydomuk/sysmon/includes/ha_info.py
mydomuk/sysmon/includes/ha_sensor.py
mydomuk/sysmon/includes/infoclass.py
mydomuk/sysmon/includes/ipmonitor.py
mydomuk/sysmon/includes/logger.py
mydomuk/sysmon/includes/mqttinfo.py
mydomuk/sysmon/includes/sensor_stats.py
mydomuk/sysmon/includes/sensors.py
mydomuk/sysmon/includes/tools.py
mydomuk/sysmon/resources/__init__.py
mydomuk/sysmon/resources/example.src
mydomuk_sysmon-1.2.23.dist-info/METADATA
mydomuk_sysmon-1.2.23.dist-info/WHEEL
mydomuk_sysmon-1.2.23.dist-info/top_level.txt
mydomuk_sysmon-1.2.23.dist-info/RECORD
