Metadata-Version: 2.4
Name: mydomuk.sysmon
Version: 1.2.23
Summary: System Monitor Tool using MQTT
Author: Richard Brent
Keywords: MQTT,monitoring,mydomuk
Classifier: License :: Free For Home Use
Classifier: Programming Language :: Python
Requires-Python: >=3.7
Requires-Dist: psutil>=5.9.4
Requires-Dist: paho-mqtt>=2.1.0
